MANIFEST.in
lreplay.pyx
setup.py
lreplay.egg-info/PKG-INFO
lreplay.egg-info/SOURCES.txt
lreplay.egg-info/dependency_links.txt
lreplay.egg-info/not-zip-safe
lreplay.egg-info/top_level.txt
replay_cpp/defines.h
replay_cpp/replay.h
replay_cpp/test.cpp