Metadata-Version: 1.0
Name: lreplay
Version: 0.1.4
Summary: lreplay
Home-page: http://bitbucket.com/fingul/loudness_replay
Author: fingul
Author-email: fingul@gmail.com
License: MIT
Platform: UNKNOWN
